{
    "AX": {
        "error": 5.651155978796414e-07,
        "error_type": "SEM",
        "filter_outliers_dict": {
            "filter_outliers": false,
            "iterations": 0,
            "std_devs": 0,
            "use_iqr_filtering": false,
            "use_standard_deviation_filtering": false
        },
        "fit": "Average",
        "fn": 10,
        "include_baseline_error": false,
        "n": 10,
        "outlier_excluded": [],
        "reviewed": true,
        "user_excluded": [],
        "value": -3.361892046882531e-06
    },
    "H1": {
        "error": 2.574936303188383e-07,
        "error_type": "SEM",
        "filter_outliers_dict": {
            "filter_outliers": false,
            "iterations": 0,
            "std_devs": 0,
            "use_iqr_filtering": false,
            "use_standard_deviation_filtering": false
        },
        "fit": "Average",
        "fn": 10,
        "include_baseline_error": false,
        "n": 10,
        "outlier_excluded": [],
        "reviewed": true,
        "user_excluded": [],
        "value": -2.701078337850049e-05
    },
    "H2": {
        "error": 6.599447202018113e-07,
        "error_type": "SEM",
        "filter_outliers_dict": {
            "filter_outliers": false,
            "iterations": 0,
            "std_devs": 0,
            "use_iqr_filtering": false,
            "use_standard_deviation_filtering": false
        },
        "fit": "Average",
        "fn": 10,
        "include_baseline_error": false,
        "n": 10,
        "outlier_excluded": [],
        "reviewed": true,
        "user_excluded": [],
        "value": -1.1414928121666889e-05
    },
    "L1": {
        "error": 2.905132647976093e-07,
        "error_type": "SEM",
        "filter_outliers_dict": {
            "filter_outliers": false,
            "iterations": 0,
            "std_devs": 0,
            "use_iqr_filtering": false,
            "use_standard_deviation_filtering": false
        },
        "fit": "Average",
        "fn": 10,
        "include_baseline_error": false,
        "n": 10,
        "outlier_excluded": [],
        "reviewed": true,
        "user_excluded": [],
        "value": -1.4557581152985223e-06
    },
    "L2": {
        "error": 0.05972157549199916,
        "error_type": "SEM",
        "filter_outliers_dict": {
            "filter_outliers": false,
            "iterations": 0,
            "std_devs": 0,
            "use_iqr_filtering": false,
            "use_standard_deviation_filtering": false
        },
        "fit": "Average",
        "fn": 10,
        "include_baseline_error": false,
        "n": 10,
        "outlier_excluded": [],
        "reviewed": true,
        "user_excluded": [],
        "value": 0.6700000107288361
    }
}