{
    "Ar36": {
        "error": 0.8478897378321868,
        "error_type": "",
        "fit": "previous",
        "references": [
            {
                "exclude": false,
                "record_id": "bu-CC-N-3871"
            }
        ],
        "value": 114.50196595263725
    },
    "Ar37": {
        "error": 3.660743384961338e-06,
        "error_type": "",
        "fit": "previous",
        "references": [
            {
                "exclude": false,
                "record_id": "bu-CC-N-3871"
            }
        ],
        "value": 1.6500662422539627e-05
    },
    "Ar38": {
        "error": 3.683509473842112e-06,
        "error_type": "",
        "fit": "previous",
        "references": [
            {
                "exclude": false,
                "record_id": "bu-CC-N-3871"
            }
        ],
        "value": -6.240750133839913e-06
    },
    "Ar39": {
        "error": 3.518931004632231e-07,
        "error_type": "",
        "fit": "previous",
        "references": [
            {
                "exclude": false,
                "record_id": "bu-CC-N-3871"
            }
        ],
        "value": 1.8380146399147366e-06
    },
    "Ar40": {
        "error": 2.055624089008162e-06,
        "error_type": "",
        "fit": "previous",
        "references": [
            {
                "exclude": false,
                "record_id": "bu-CC-N-3871"
            }
        ],
        "value": 8.896036970142938e-05
    }
}